aiohttp_apispec/__init__.py
aiohttp_apispec/apispec.py
aiohttp_apispec/decorators.py
aiohttp_apispec/middlewares.py
aiohttp_apispec/static/favicon-16x16.png
aiohttp_apispec/static/favicon-32x32.png
aiohttp_apispec/static/index.html
aiohttp_apispec/static/oauth2-redirect.html
aiohttp_apispec/static/swagger-ui-bundle.js
aiohttp_apispec/static/swagger-ui-bundle.js.map
aiohttp_apispec/static/swagger-ui-standalone-preset.js
aiohttp_apispec/static/swagger-ui-standalone-preset.js.map
aiohttp_apispec/static/swagger-ui.css
aiohttp_apispec/static/swagger-ui.css.map
aiohttp_apispec/static/swagger-ui.js
aiohttp_apispec/static/swagger-ui.js.map
aiohttp_apispec/utils.py
geolibs_aiohttp_apispec-0.0.2.dist-info/LICENSE
geolibs_aiohttp_apispec-0.0.2.dist-info/WHEEL
geolibs_aiohttp_apispec-0.0.2.dist-info/METADATA
geolibs_aiohttp_apispec-0.0.2.dist-info/RECORD
